quantumstatetomography/__init__.py
quantumstatetomography/rhoproperties.py
quantumstatetomography/tomography.py
quantumstatetomography/tomohelpers.py
quantumstatetomography-0.0.2.dist-info/LICENSE
quantumstatetomography-0.0.2.dist-info/METADATA
quantumstatetomography-0.0.2.dist-info/WHEEL
quantumstatetomography-0.0.2.dist-info/top_level.txt
quantumstatetomography-0.0.2.dist-info/RECORD
