Metadata-Version: 2.1
Name: quantumstatetomography
Version: 0.0.2
Summary: A python package used to perform quantum state tomography.
Home-page: UNKNOWN
Author: Lana Bozanic
Author-email: lbozanic@uottawa.ca
License: UNKNOWN
Keywords: python
Platform: UNKNOWN
Classifier: Programming Language :: Python :: 3
Classifier: Operating System :: MacOS :: MacOS X
Classifier: Operating System :: Microsoft :: Windows
Requires-Dist: numpy
Requires-Dist: qutip
Requires-Dist: matplotlib
Requires-Dist: scipy
